[
    {
        "id": 1,
        "name": "Bordeaux Maritime",
        "description": "",
        "picture": "bdx-maritime.jpg",
        "rank": 0,
        "created_at": "2023-05-08 13:00:00"
    },
    {
        "id": 2,
        "name": "Bordeaux La Bastide",
        "description": "",
        "picture": "bdx-labastide.jpg",
        "rank": 0,
        "created_at": "2023-05-08 13:00:00"
    },
    {
        "id": 3,
        "name": "Bordeaux Chartrons - Jardin Public",
        "description": "",
        "picture": "bdx-chartrons.jpg",
        "rank": 0,
        "created_at": "2023-05-09 13:00:00"
    },
    {
        "id": 4,
        "name": "Bordeaux Centre",
        "description": "",
        "picture": "bdx-centre.jpg",
        "rank": 0,
        "created_at": "2023-05-10 13:00:00"
    },
    {
        "id": 5,
        "name": "Bordeaux Caudéran",
        "description": "",
        "picture": "bdx-cauderan.jpg",
        "rank": 0,
        "created_at": "2023-05-10 13:00:00"
    },
    {
        "id": 6,
        "name": "Bordeaux Saint Augustin - Tauzin",
        "description": "",
        "picture": "bdx-staugustin.jpg",
        "rank": 0,
        "created_at": "2023-05-10 13:00:00"
    },
    {
        "id": 7,
        "name": "Bordeaux Nansouty - Saint-Genès",
        "description": "",
        "picture": "bdx-nansouty.jpg",
        "rank": 0,
        "created_at": "2023-05-10 13:00:00"
    },
    {
        "id": 8,
        "name": "Bordeaux Sud",
        "description": "",
        "picture": "bdx-sud.jpg",
        "rank": 0,
        "created_at": "2023-05-12 13:00:00"
    },
    {
        "id": 9,
        "name": "Le Bouscat - Bruges",
        "description": "",
        "picture": "le-bouscat.jpg",
        "rank": 0,
        "created_at": "2023-05-14 13:00:00"
    },
    {
        "id": 10,
        "name": "Mérignac",
        "description": "",
        "picture": "merignac.jpg",
        "rank": 0,
        "created_at": "2023-05-14 13:00:00"
    },
    {
        "id": 11,
        "name": "Pessac",
        "description": "",
        "picture": "pessac.jpg",
        "rank": 0,
        "created_at": "2023-05-18 13:00:00"
    },
    {
        "id": 12,
        "name": "Talence - Bègles",
        "description": "",
        "picture": "talence.jpg",
        "rank": 0,
        "created_at": "2023-05-18 13:00:00"
    },
    {
        "id": 13,
        "name": "Lormont - Cenon - Floirac",
        "description": "",
        "picture": "lormont.jpg",
        "rank": 0,
        "created_at": "2023-05-19 13:00:00"
    },    
    {
        "id": 14,
        "name": "Aglomération Extra Rocade",
        "description": "",
        "picture": "bdx-environs.jpg",
        "rank": 0,
        "created_at": "2023-05-20 13:00:00"
    }
]